ConverterBOTDA/__init__.py
ConverterBOTDA/batch.py
ConverterBOTDA/functions.py
ConverterBOTDA/main.py
ConverterBOTDA/split.py
converterbotda-1.1.1.dist-info/entry_points.txt
converterbotda-1.1.1.dist-info/METADATA
converterbotda-1.1.1.dist-info/WHEEL
converterbotda-1.1.1.dist-info/RECORD
