Metadata-Version: 2.3
Name: converterbotda
Version: 1.1.1
Summary: Pacchetto script per convertire files json salvati da sw BOTDA a h5.
Author: Marco Brunero
Author-email: marco.brunero@cohaerentia.com
Requires-Python: >3.10,<4.0
Classifier: Programming Language :: Python :: 3
Classifier: Programming Language :: Python :: 3.11
Classifier: Programming Language :: Python :: 3.12
Classifier: Programming Language :: Python :: 3.13
Requires-Dist: h5py (>=3.10.0,<4.0.0)
Requires-Dist: ipywidgets (>=8.1.1,<9.0.0)
Requires-Dist: readerbotda (>=1.3.3,<2.0.0)
Requires-Dist: typer (>=0.15.2,<0.16.0)
